{
  "domain": "zoominfo.com",
  "queries": [
    "digital marketing agency founder contact"
  ],
  "fetched_at": "2026-03-19T04:14:14.041226Z",
  "serp_results": [
    {
      "url": "https://www.zoominfo.com/c/the-digital-marketing-agency--consulting-company-llc/1315992247",
      "title": "The Digital Marketing Agency & Consulting - ZoomInfo",
      "snippet": "Headquarters. 422 N Capitol Ave, San Jose, California, 95133, United States ; Phone Number. (510) 706-3755 ; Website. www.digitalmarketingagency-consultant.com ...",
      "query": "digital marketing agency founder contact",
      "page_index": 1,
      "rank_on_page": 4,
      "fetched_at": "2026-03-19T04:13:48.193823Z",
      "domain": "zoominfo.com"
    }
  ],
  "scoring_prompt_fingerprint": "1a59f9976ea3e4d79dc9a22776fd790359a43f3e5b977bc72e4468cca2d21fff"
}